{
    "sections": [
        {
            "component": "About",
            "path": "/about",
            "headerTitle": "A propos"
        },
        {
            "component": "Skills",
            "path": "/skills",
            "headerTitle": "Competences"
        },
        {
            "component": "Education",
            "path": "/education",
            "headerTitle": "Etudes"
        },
        {
            "component": "Experience",
            "path": "/experience",
            "headerTitle": "Experience"
        },
        {
            "component": "Projects",
            "path": "/projects",
            "headerTitle": "Projets"
        }
    ]
}